pexpect-stubs/ANSI.pyi
pexpect-stubs/FSM.pyi
pexpect-stubs/METADATA.toml
pexpect-stubs/__init__.pyi
pexpect-stubs/_async.pyi
pexpect-stubs/exceptions.pyi
pexpect-stubs/expect.pyi
pexpect-stubs/fdpexpect.pyi
pexpect-stubs/popen_spawn.pyi
pexpect-stubs/pty_spawn.pyi
pexpect-stubs/pxssh.pyi
pexpect-stubs/py.typed
pexpect-stubs/replwrap.pyi
pexpect-stubs/run.pyi
pexpect-stubs/screen.pyi
pexpect-stubs/socket_pexpect.pyi
pexpect-stubs/spawnbase.pyi
pexpect-stubs/utils.pyi
types_pexpect-4.9.0.20250809.dist-info/licenses/LICENSE
types_pexpect-4.9.0.20250809.dist-info/METADATA
types_pexpect-4.9.0.20250809.dist-info/WHEEL
types_pexpect-4.9.0.20250809.dist-info/top_level.txt
types_pexpect-4.9.0.20250809.dist-info/RECORD
